abattlemetrics/__init__.py
abattlemetrics/client.py
abattlemetrics/datapoint.py
abattlemetrics/errors.py
abattlemetrics/iterators.py
abattlemetrics/limiter.py
abattlemetrics/mixins.py
abattlemetrics/player.py
abattlemetrics/server.py
abattlemetrics/session.py
abattlemetrics/utils.py
abattlemetrics-0.6.0.post1.dist-info/LICENSE
abattlemetrics-0.6.0.post1.dist-info/METADATA
abattlemetrics-0.6.0.post1.dist-info/WHEEL
abattlemetrics-0.6.0.post1.dist-info/top_level.txt
abattlemetrics-0.6.0.post1.dist-info/RECORD
