Metadata-Version: 2.1
Name: abattlemetrics
Version: 0.6.0.post1
Summary: An asyncio wrapper for the battlemetrics API
Home-page: https://github.com/thegamecracks/abattlemetrics
Author: thegamecracks
License: MIT
Classifier: Development Status :: 3 - Alpha
Classifier: Framework :: AsyncIO
Classifier: Framework :: aiohttp
Classifier: Intended Audience :: Developers
Classifier: License :: OSI Approved :: MIT License
Classifier: Programming Language :: Python
Classifier: Programming Language :: Python :: 3
Classifier: Programming Language :: Python :: 3.8
Classifier: Topic :: Internet
Classifier: Topic :: Internet :: WWW/HTTP
Requires-Python: >=3.8
License-File: LICENSE
Requires-Dist: aiohttp
Requires-Dist: python-dateutil
